mplayer/__init__.py
mplayer/async.py
mplayer/core.py
mplayer/gevent1.py
mplayer/gtk2.py
mplayer/misc.py
mplayer/mtypes.py
mplayer/qt4.py
mplayer.py-0.7.2.post1.dist-info/LICENSE
mplayer.py-0.7.2.post1.dist-info/METADATA
mplayer.py-0.7.2.post1.dist-info/WHEEL
mplayer.py-0.7.2.post1.dist-info/top_level.txt
mplayer.py-0.7.2.post1.dist-info/RECORD
